hsi2rgb/__init__.py
hsi2rgb/hsi2rgb.py
hsi2rgb-0.1.1.dist-info/METADATA
hsi2rgb-0.1.1.dist-info/WHEEL
hsi2rgb-0.1.1.dist-info/licenses/LICENSE
hsi2rgb-0.1.1.dist-info/RECORD
